flask_api_cache/__init__.py
flask_api_cache/api_cache.py
flask_api_cache-0.1.1.dist-info/METADATA
flask_api_cache-0.1.1.dist-info/WHEEL
flask_api_cache-0.1.1.dist-info/top_level.txt
flask_api_cache-0.1.1.dist-info/RECORD
