Metadata-Version: 2.1
Name: flask-api-cache
Version: 0.1.1
Summary: A tool for flask api cache with args
Home-page: https://github.com/chienfeng0719/flask-api-cache
Author: Jimmy Yeh
Author-email: chienfeng0719@hotmail.com
License: UNKNOWN
Platform: UNKNOWN
Classifier: Programming Language :: Python :: 3
Classifier: License :: OSI Approved :: MIT License
Classifier: Operating System :: OS Independent
Requires-Python: >=3.6
Requires-Dist: Flask (==1.1.2)
Requires-Dist: memoization (==0.3.1)
